TechTribe/decorator.py
TechTribe/handlers.py
TechTribe/main.py
TechTribe/dialogs/__init__.py
TechTribe/dialogs/ask_command_dialog.py
TechTribe/dialogs/ask_dialog_usage.py
TechTribe/dialogs/print_text.py
TechTribe/models/__init__.py
TechTribe/models/address_book.py
TechTribe/models/colors.py
TechTribe/models/commands.py
TechTribe/models/field.py
TechTribe/models/fields.py
TechTribe/models/record.py
techtribe_addressbook-1.0.3.dist-info/LICENSE
techtribe_addressbook-1.0.3.dist-info/METADATA
techtribe_addressbook-1.0.3.dist-info/WHEEL
techtribe_addressbook-1.0.3.dist-info/entry_points.txt
techtribe_addressbook-1.0.3.dist-info/top_level.txt
techtribe_addressbook-1.0.3.dist-info/RECORD
