Metadata-Version: 2.1
Name: techtribe-addressbook
Version: 1.0.3
Summary: Save your data easy and convenient
License: The MIT License (MIT)
Project-URL: Homepage, https://github.com/Oldestgraf/TechTribe
Keywords: addressbook,techtribe
Classifier: License :: OSI Approved :: MIT License
Classifier: Programming Language :: Python :: 3
Classifier: Operating System :: OS Independent
License-File: LICENSE
Requires-Dist: prompt-toolkit ==3.0.43
Requires-Dist: wcwidth ==0.2.13
